README.md
setup.py
sl_api_client/__init__.py
sl_api_client/api_client.py
sl_api_client/configuration.py
sl_api_client/rest.py
sl_api_client.egg-info/PKG-INFO
sl_api_client.egg-info/SOURCES.txt
sl_api_client.egg-info/dependency_links.txt
sl_api_client.egg-info/requires.txt
sl_api_client.egg-info/top_level.txt
sl_api_client/api/__init__.py
sl_api_client/api/analytics_api.py
sl_api_client/api/auth_api.py
sl_api_client/api/b_territory_api.py
sl_api_client/api/calendar_api.py
sl_api_client/api/catalogs_api.py
sl_api_client/api/collections_api.py
sl_api_client/api/discount_api.py
sl_api_client/api/documents_api.py
sl_api_client/api/event_api.py
sl_api_client/api/file_api.py
sl_api_client/api/infosystems_api.py
sl_api_client/api/loyalty_api.py
sl_api_client/api/message_api.py
sl_api_client/api/orders_api.py
sl_api_client/api/orders_v2_admin_api.py
sl_api_client/api/orders_v2_client_api.py
sl_api_client/api/pay_api.py
sl_api_client/api/payments_v2_api.py
sl_api_client/api/permissions_api.py
sl_api_client/api/pizzaman_api.py
sl_api_client/api/router_api.py
sl_api_client/api/service_api.py
sl_api_client/api/settings_api.py
sl_api_client/api/shininvest_api.py
sl_api_client/api/shops_api.py
sl_api_client/api/space_api.py
sl_api_client/api/statistics_api.py
sl_api_client/api/support_api.py
sl_api_client/api/talan_api.py
sl_api_client/api/talan_auth_api.py
sl_api_client/api/users_api.py
sl_api_client/models/__init__.py
sl_api_client/models/address.py
sl_api_client/models/after_search.py
sl_api_client/models/aggregation.py
sl_api_client/models/analytics_push_response.py
sl_api_client/models/analytics_response.py
sl_api_client/models/apple_pay_register_request.py
sl_api_client/models/balance_model.py
sl_api_client/models/base_mailing_item.py
sl_api_client/models/base_query.py
sl_api_client/models/base_search.py
sl_api_client/models/base_template_message.py
sl_api_client/models/base_template_message_template.py
sl_api_client/models/batch_errors_model.py
sl_api_client/models/batch_update_users_model.py
sl_api_client/models/batch_user_query.py
sl_api_client/models/body.py
sl_api_client/models/body1.py
sl_api_client/models/body2.py
sl_api_client/models/body3.py
