Metadata-Version: 1.0
Name: sl-api-client
Version: 1.2.130
Summary: Napoleon S&amp;L API
Home-page: https://gitlab.itnap.ru/shop-loyalty/sl-service-client/py-sl-service-client-asyncio
Author: UNKNOWN
Author-email: ag@napoleonit.ru
License: UNKNOWN
Keywords: Swagger,Napoleon S&amp;L API
Platform: UNKNOWN
